tri/__init__.py
tri/bi.py
tri/tri.py
tribi-1.0.4.dist-info/LICENSE
tribi-1.0.4.dist-info/METADATA
tribi-1.0.4.dist-info/WHEEL
tribi-1.0.4.dist-info/top_level.txt
tribi-1.0.4.dist-info/RECORD
