Metadata-Version: 2.1
Name: tribi
Version: 1.0.4
Summary: Prettier error handling for Python
Home-page: https://github.com/starsflower/python-tri
Author: starsflower
License: MIT
Platform: UNKNOWN
Classifier: License :: OSI Approved :: MIT License
Classifier: Programming Language :: Python :: 3
License-File: LICENSE
